{
  "palm_center": [
    0.4792610354983704,
    0.2509155373671492
  ],
  "fingertips": [
    [
      0.15780477055351558,
      0.20544218854556678
    ],
    [
      0.3012388728675806,
      0.34326774779164404
    ],
    [
      0.36717451880116314,
      0.3451518089582716
    ],
    [
      0.4740820821962658,
      0.2792609776916589
    ],
    [
      0.6721349348745025,
      0.12218946145564759
    ]
  ],
  "hand_type": "unknown",
  "extended_count": 2,
  "finger_states": [
    {
      "index": 0,
      "state": "extended",
      "distance_ratio": 1.7410757302445816
    },
    {
      "index": 1,
      "state": "half-bent",
      "distance_ratio": 1.0755207498648522
    },
    {
      "index": 2,
      "state": "folded",
      "distance_ratio": 0.7853166947077721
    },
    {
      "index": 3,
      "state": "folded",
      "distance_ratio": 0.15452795792783836
    },
    {
      "index": 4,
      "state": "extended",
      "distance_ratio": 1.2435588672549556
    }
  ],
  "mode": "mediapipe"
}